azulene_opal-0.3.0.dist-info/licenses/LICENSE
opal/__init__.py
opal/auth.py
opal/config.py
opal/jobs.py
opal/main.py
opal/utils.py
azulene_opal-0.3.0.dist-info/METADATA
azulene_opal-0.3.0.dist-info/WHEEL
azulene_opal-0.3.0.dist-info/entry_points.txt
azulene_opal-0.3.0.dist-info/top_level.txt
azulene_opal-0.3.0.dist-info/RECORD
