Metadata-Version: 2.4
Name: azulene-opal
Version: 0.3.0
Summary: A CLI and Python library to interact with Azulene Opal
Author-email: Azulene Labs <contact@azulenelabs.com>
Project-URL: Homepage, https://www.azulenelabs.com/
Project-URL: Repository, https://github.com/Azulene-Labs/opal-cli
Requires-Python: >=3.8
License-File: LICENSE
Requires-Dist: typer
Requires-Dist: httpx
Requires-Dist: supabase
Requires-Dist: rich
Dynamic: license-file
